<annotation>
	<folder>my-project-name</folder>
	<filename>OB_101.jpg</filename>
	<path>/my-project-name/OB_101.jpg</path>
	<source>
		<database>Unspecified</database>
	</source>
	<size>
		<width>3072</width>
		<height>4080</height>
		<depth>3</depth>
	</size>
	<object>
		<name>fuse</name>
		<pose>Unspecified</pose>
		<truncated>0</truncated>
		<difficult>0</difficult>
		<bndbox>
			<xmin>1268</xmin>
			<ymin>1219</ymin>
			<xmax>2040</xmax>
			<ymax>1617</ymax>
		</bndbox>
	</object>
	<object>
		<name>fuse</name>
		<pose>Unspecified</pose>
		<truncated>0</truncated>
		<difficult>0</difficult>
		<bndbox>
			<xmin>1252</xmin>
			<ymin>1788</ymin>
			<xmax>1983</xmax>
			<ymax>2211</ymax>
		</bndbox>
	</object>
	<object>
		<name>ciruit_breaker</name>
		<pose>Unspecified</pose>
		<truncated>0</truncated>
		<difficult>0</difficult>
		<bndbox>
			<xmin>2454</xmin>
			<ymin>1057</ymin>
			<xmax>3072</xmax>
			<ymax>2406</ymax>
		</bndbox>
	</object>
</annotation>