<annotation>
	<folder>my-project-name</folder>
	<filename>OB_051.jpg</filename>
	<path>/my-project-name/OB_051.jpg</path>
	<source>
		<database>Unspecified</database>
	</source>
	<size>
		<width>3072</width>
		<height>4080</height>
		<depth>3</depth>
	</size>
	<object>
		<name>fuse</name>
		<pose>Unspecified</pose>
		<truncated>0</truncated>
		<difficult>0</difficult>
		<bndbox>
			<xmin>707</xmin>
			<ymin>1374</ymin>
			<xmax>1260</xmax>
			<ymax>1666</ymax>
		</bndbox>
	</object>
	<object>
		<name>fuse</name>
		<pose>Unspecified</pose>
		<truncated>0</truncated>
		<difficult>0</difficult>
		<bndbox>
			<xmin>666</xmin>
			<ymin>1764</ymin>
			<xmax>1219</xmax>
			<ymax>2081</ymax>
		</bndbox>
	</object>
	<object>
		<name>ciruit_breaker</name>
		<pose>Unspecified</pose>
		<truncated>0</truncated>
		<difficult>0</difficult>
		<bndbox>
			<xmin>1609</xmin>
			<ymin>1292</ymin>
			<xmax>2113</xmax>
			<ymax>2268</ymax>
		</bndbox>
	</object>
</annotation>